[
    {
    "totleTime":1,
    "targetScop":500,
    "data":[
        {
            "x":-300,
            "y":-200,
            "isBoom":false,
            "scope":0,
            "typeNum":1,
            "coin":100,
            "speed":40,
            "isEnd":false
        },
        {
            "x":20,
            "y":-200,
            "isBoom":false,
            "scope":0,
            "typeNum":2,
            "coin":200,
            "speed":60,
            "isEnd":false
        },
        {
            "x":185,
            "y":-155,
            "isBoom":false,
            "scope":0,
            "typeNum":1,
            "coin":50,
            "speed":40,
            "isEnd":false
        },
        {
            "x":330,
            "y":-155,
            "isBoom":false,
            "scope":0,
            "typeNum":3,
            "coin":50,
            "speed":20,
            "isEnd":false
        },
        {
            "x":-200,
            "y":-175,
            "isBoom":false,
            "scope":0,
            "typeNum":3,
            "coin":100,
            "speed":50,
            "isEnd":false
        }
    ]
    }
]